repo_activity/__init__.py
repo_activity/score.py
repo_activity_score-0.0.4.dist-info/LICENSE
repo_activity_score-0.0.4.dist-info/METADATA
repo_activity_score-0.0.4.dist-info/WHEEL
repo_activity_score-0.0.4.dist-info/top_level.txt
repo_activity_score-0.0.4.dist-info/RECORD
