Metadata-Version: 2.1
Name: repo-activity-score
Version: 0.0.4
Summary: Python implementation of the InnerSourceCommons Repository Activity Score pattern algorithm
Home-page: https://github.com/InnerSourceCommons/repo-activity-score
Author: André Correia & InnerSourceCommons
Author-email: andrecorreia@pm.me
License: UNKNOWN
Project-URL: Bug Tracker, https://github.com/InnerSourceCommons/repo-activity-score/issues
Platform: UNKNOWN
Classifier: Programming Language :: Python :: 3
Classifier: License :: OSI Approved :: MIT License
Classifier: Operating System :: OS Independent
Requires-Python: >=3.6
License-File: LICENSE
